mre/Anchor.py
mre/Comment.py
mre/Group.py
mre/Lookaround.py
mre/Quantifier.py
mre/Regex.py
mre/RegexBase.py
mre/Set.py
mre/__init__.py
mre/helper/Range.py
mre/helper/__init__.py
mre-0.12.0.dist-info/LICENSE
mre-0.12.0.dist-info/METADATA
mre-0.12.0.dist-info/WHEEL
mre-0.12.0.dist-info/top_level.txt
mre-0.12.0.dist-info/RECORD
