Metadata-Version: 2.1
Name: mre
Version: 0.12.0
Summary: Maker Regular Expressions
Home-page: https://github.com/alvarofpp/mre
Author: Álvaro Ferreira Pires de Paiva
Author-email: alvarofepipa@gmail.com
License: UNKNOWN
Platform: UNKNOWN
Classifier: Programming Language :: Python :: 3
Classifier: License :: OSI Approved :: MIT License
Classifier: Operating System :: OS Independent
